MANIFEST.in
setup.cfg
setup.py
benri/__init__.py
benri/config.py
benri/db.py
benri/lifetime.py
benri/log.py
benri/service.py
benri/spool.py
benri/threadstage.py
benri/utils.py
benri.egg-info/PKG-INFO
benri.egg-info/SOURCES.txt
benri.egg-info/dependency_links.txt
benri.egg-info/entry_points.txt
benri.egg-info/not-zip-safe
benri.egg-info/requires.txt
benri.egg-info/top_level.txt
benri/app/__init__.py
benri/app/json.py
benri/app/wsgiapp.py
benri/app/wsgicollection.py
benri/security/__init__.py
benri/security/authfilter.py
benri/security/authorization.py
benri/security/userdb.py
benri/templates/__init__.py
benri/templates/benri/+package+/MANIFEST.in
benri/templates/benri/+package+/setup.py_tmpl
benri/templates/benri/+package+.client/MANIFEST.in
benri/templates/benri/+package+.client/setup.py_tmpl
benri/templates/benri/+package+.client/+package+/__init__.py
benri/templates/benri/+package+.client/+package+/client/__init__.py_tmpl
benri/templates/benri/+package+.client/+package+/client/client.py
benri/templates/benri/+package+.client/scripts/+package+-client_tmpl
benri/templates/benri/+package+/+package+/__init__.py
benri/templates/benri/+package+/+package+/service/__init__.py_tmpl
benri/templates/benri/+package+/+package+/service/example.py_tmpl
benri/templates/benri/+package+/+package+/service/serve.py_tmpl
benri/templates/benri/+package+/etc/+package+.cfg_tmpl
benri/templates/benri/+package+/scripts/+package+_tmpl
benri/templates/benri/+package+/tests/test_example.py_tmpl
benri/wsgiserver/__init__.py
benri/wsgiserver/ssl_builtin.py
benri/wsgiserver/ssl_pyopenssl.py