Metadata-Version: 1.0
Name: benri
Version: 0.0.4
Summary: A REST-service creation framework.
Home-page: UNKNOWN
Author: Mikael Hoegqvist
Author-email: hoegqvist@zib.de
License: UNKNOWN
Platform: UNKNOWN
Classifier: Development Status :: 4 - Beta
Classifier: Environment :: Web Environment
Classifier: Intended Audience :: Developers
Classifier: Programming Language :: Python
Classifier: Topic :: Internet :: WWW/HTTP
Classifier: Topic :: Software Development :: Libraries
